confitti/__init__.py
confitti/confitti.py
confitti-0.2.1.dist-info/METADATA
confitti-0.2.1.dist-info/WHEEL
confitti-0.2.1.dist-info/licenses/LICENSE
confitti-0.2.1.dist-info/RECORD
