Metadata-Version: 2.3
Name: confitti
Version: 0.2.1
Summary: Fit conic sections (ellipse, parabola, hyperbola) to a set of 2d points
Author-email: William Henney <will@henney.org>
License-File: LICENSE
Requires-Python: >=3.8
Requires-Dist: emcee>=3.1.4
Requires-Dist: lmfit>=1.2.2
Requires-Dist: numpy>=1.26.4
Requires-Dist: pyyaml>=6.0.2
Requires-Dist: scipy>=1.13.0
